{
  "plumbers": [
    {
      "id": 1,
      "name": "Maude"
    },
    {
      "id": 2,
      "name": "Merle"
    },
    {
      "id": 3,
      "name": "Danny"
    }
  ],
  "completions": [
    {
      "requestId": 4,
      "plumberId": 1,
      "date_created": "9/28/2022",
      "id": 1
    }
  ],
  "requests": [
    {
      "description": "test123",
      "address": "test",
      "budget": "500",
      "neededBy": "2022-09-25",
      "isComplete": false,
      "plumberId": "2",
      "id": 1
    },
    {
      "description": "test 1234",
      "address": "test",
      "budget": "500",
      "neededBy": "2022-10-01",
      "isComplete": false,
      "plumberId": "1",
      "id": 2
    },
    {
      "description": "test",
      "address": "test",
      "budget": "500",
      "neededBy": "2022-10-01",
      "isComplete": false,
      "plumberId": "1",
      "id": 3
    },
    {
      "description": "here is a new request testing",
      "address": "123 test way",
      "budget": "500",
      "neededBy": "2022-09-28",
      "isComplete": true,
      "plumberId": "1",
      "id": 4
    }
  ]
}